<?xml version="1.0" encoding="UTF-8"?>

<!-- DTD for the XMLBIF 0.3 format -->
<!DOCTYPE BIF [
<!ELEMENT BIF ( NETWORK )*>
<!ATTLIST BIF VERSION CDATA #REQUIRED>
   <!ELEMENT NETWORK ( NAME, ( PROPERTY | VARIABLE | DEFINITION )* )>
      <!ELEMENT NAME (#PCDATA)>
        <!ELEMENT VARIABLE ( NAME, ( OUTCOME |  PROPERTY )* ) >
          <!ATTLIST VARIABLE TYPE (nature|decision|utility) "nature">
           <!ELEMENT OUTCOME (#PCDATA)>
            <!ELEMENT DEFINITION ( FOR | GIVEN | TABLE | PROPERTY )* >
              <!ELEMENT FOR (#PCDATA)>
                <!ELEMENT GIVEN (#PCDATA)>
                  <!ELEMENT TABLE (#PCDATA)>
                    <!ELEMENT PROPERTY (#PCDATA)>
                      ]>
<BIF VERSION="0.3">
<NETWORK>
<NAME>Reco</NAME>
<VARIABLE TYPE="nature">
	<NAME>v1</NAME>
	<OUTCOME>0</OUTCOME>
	<OUTCOME>2</OUTCOME>
	<OUTCOME>1</OUTCOME>
</VARIABLE>

<VARIABLE TYPE="nature">
	<NAME>v2</NAME>
	<OUTCOME>1</OUTCOME>
	<OUTCOME>2</OUTCOME>
	<OUTCOME>0</OUTCOME>
	<OUTCOME>3</OUTCOME>
	<OUTCOME>8</OUTCOME>
</VARIABLE>

<VARIABLE TYPE="nature">
	<NAME>v3</NAME>
	<OUTCOME>0</OUTCOME>
	<OUTCOME>1</OUTCOME>
</VARIABLE>

<VARIABLE TYPE="nature">
	<NAME>v4</NAME>
	<OUTCOME>1</OUTCOME>
	<OUTCOME>0</OUTCOME>
</VARIABLE>

<VARIABLE TYPE="nature">
	<NAME>v5</NAME>
	<OUTCOME>1</OUTCOME>
	<OUTCOME>0</OUTCOME>
</VARIABLE>

<VARIABLE TYPE="nature">
	<NAME>v6</NAME>
	<OUTCOME>1</OUTCOME>
	<OUTCOME>0</OUTCOME>
</VARIABLE>

<VARIABLE TYPE="nature">
	<NAME>v7</NAME>
	<OUTCOME>0</OUTCOME>
	<OUTCOME>1</OUTCOME>
	<OUTCOME>3</OUTCOME>
</VARIABLE>

<VARIABLE TYPE="nature">
	<NAME>v8</NAME>
	<OUTCOME>0</OUTCOME>
	<OUTCOME>1</OUTCOME>
</VARIABLE>

<VARIABLE TYPE="nature">
	<NAME>v9</NAME>
	<OUTCOME>1</OUTCOME>
	<OUTCOME>0</OUTCOME>
</VARIABLE>

<VARIABLE TYPE="nature">
	<NAME>v10</NAME>
	<OUTCOME>1</OUTCOME>
	<OUTCOME>0</OUTCOME>
</VARIABLE>

<VARIABLE TYPE="nature">
	<NAME>v11</NAME>
	<OUTCOME>1</OUTCOME>
	<OUTCOME>0</OUTCOME>
</VARIABLE>

<VARIABLE TYPE="nature">
	<NAME>v12</NAME>
	<OUTCOME>0</OUTCOME>
	<OUTCOME>1</OUTCOME>
</VARIABLE>

<VARIABLE TYPE="nature">
	<NAME>v13</NAME>
	<OUTCOME>1</OUTCOME>
	<OUTCOME>0</OUTCOME>
</VARIABLE>

<VARIABLE TYPE="nature">
	<NAME>v14</NAME>
	<OUTCOME>0</OUTCOME>
	<OUTCOME>1</OUTCOME>
</VARIABLE>

<VARIABLE TYPE="nature">
	<NAME>v15</NAME>
	<OUTCOME>1</OUTCOME>
	<OUTCOME>0</OUTCOME>
</VARIABLE>

<VARIABLE TYPE="nature">
	<NAME>v16</NAME>
	<OUTCOME>1</OUTCOME>
	<OUTCOME>0</OUTCOME>
</VARIABLE>

<VARIABLE TYPE="nature">
	<NAME>v17</NAME>
	<OUTCOME>0</OUTCOME>
	<OUTCOME>2</OUTCOME>
	<OUTCOME>1</OUTCOME>
	<OUTCOME>-1</OUTCOME>
</VARIABLE>

<VARIABLE TYPE="nature">
	<NAME>v18</NAME>
	<OUTCOME>0</OUTCOME>
	<OUTCOME>1</OUTCOME>
</VARIABLE>

<VARIABLE TYPE="nature">
	<NAME>v19</NAME>
	<OUTCOME>9</OUTCOME>
	<OUTCOME>12</OUTCOME>
	<OUTCOME>5</OUTCOME>
	<OUTCOME>7</OUTCOME>
	<OUTCOME>4</OUTCOME>
	<OUTCOME>11</OUTCOME>
	<OUTCOME>3</OUTCOME>
	<OUTCOME>1</OUTCOME>
	<OUTCOME>6</OUTCOME>
	<OUTCOME>2</OUTCOME>
	<OUTCOME>0</OUTCOME>
	<OUTCOME>13</OUTCOME>
	<OUTCOME>10</OUTCOME>
</VARIABLE>

<VARIABLE TYPE="nature">
	<NAME>v21</NAME>
	<OUTCOME>0</OUTCOME>
	<OUTCOME>1</OUTCOME>
</VARIABLE>

<VARIABLE TYPE="nature">
	<NAME>v23</NAME>
	<OUTCOME>999</OUTCOME>
	<OUTCOME>0</OUTCOME>
</VARIABLE>

<VARIABLE TYPE="nature">
	<NAME>v24</NAME>
	<OUTCOME>1</OUTCOME>
	<OUTCOME>8</OUTCOME>
	<OUTCOME>2</OUTCOME>
	<OUTCOME>0</OUTCOME>
	<OUTCOME>3</OUTCOME>
</VARIABLE>

<VARIABLE TYPE="nature">
	<NAME>v25</NAME>
	<OUTCOME>0</OUTCOME>
	<OUTCOME>1</OUTCOME>
</VARIABLE>

<VARIABLE TYPE="nature">
	<NAME>v26</NAME>
	<OUTCOME>0</OUTCOME>
	<OUTCOME>1</OUTCOME>
</VARIABLE>

<VARIABLE TYPE="nature">
	<NAME>v27</NAME>
	<OUTCOME>2</OUTCOME>
	<OUTCOME>0</OUTCOME>
	<OUTCOME>1</OUTCOME>
</VARIABLE>

<VARIABLE TYPE="nature">
	<NAME>v28</NAME>
	<OUTCOME>0</OUTCOME>
	<OUTCOME>2</OUTCOME>
	<OUTCOME>1</OUTCOME>
</VARIABLE>

<VARIABLE TYPE="nature">
	<NAME>v29</NAME>
	<OUTCOME>999</OUTCOME>
	<OUTCOME>-1</OUTCOME>
</VARIABLE>

<VARIABLE TYPE="nature">
	<NAME>v30</NAME>
	<OUTCOME>999</OUTCOME>
	<OUTCOME>-1</OUTCOME>
</VARIABLE>

<VARIABLE TYPE="nature">
	<NAME>v31</NAME>
	<OUTCOME>0</OUTCOME>
	<OUTCOME>1</OUTCOME>
</VARIABLE>

<VARIABLE TYPE="nature">
	<NAME>v32</NAME>
	<OUTCOME>1</OUTCOME>
	<OUTCOME>0</OUTCOME>
</VARIABLE>

<VARIABLE TYPE="nature">
	<NAME>v33</NAME>
	<OUTCOME>0</OUTCOME>
	<OUTCOME>1</OUTCOME>
</VARIABLE>

<VARIABLE TYPE="nature">
	<NAME>v34</NAME>
	<OUTCOME>999</OUTCOME>
	<OUTCOME>-1</OUTCOME>
</VARIABLE>

<VARIABLE TYPE="nature">
	<NAME>v35</NAME>
	<OUTCOME>0</OUTCOME>
	<OUTCOME>1</OUTCOME>
</VARIABLE>

<VARIABLE TYPE="nature">
	<NAME>v36</NAME>
	<OUTCOME>0</OUTCOME>
	<OUTCOME>1</OUTCOME>
	<OUTCOME>-1</OUTCOME>
</VARIABLE>

<VARIABLE TYPE="nature">
	<NAME>v37</NAME>
	<OUTCOME>0</OUTCOME>
	<OUTCOME>1</OUTCOME>
</VARIABLE>

<VARIABLE TYPE="nature">
	<NAME>v38</NAME>
	<OUTCOME>0</OUTCOME>
	<OUTCOME>2</OUTCOME>
	<OUTCOME>1</OUTCOME>
</VARIABLE>

<VARIABLE TYPE="nature">
	<NAME>v39</NAME>
	<OUTCOME>1</OUTCOME>
	<OUTCOME>0</OUTCOME>
</VARIABLE>

<VARIABLE TYPE="nature">
	<NAME>v40</NAME>
	<OUTCOME>999</OUTCOME>
	<OUTCOME>-1</OUTCOME>
</VARIABLE>

<VARIABLE TYPE="nature">
	<NAME>v41</NAME>
	<OUTCOME>1</OUTCOME>
	<OUTCOME>0</OUTCOME>
</VARIABLE>

<VARIABLE TYPE="nature">
	<NAME>v42</NAME>
	<OUTCOME>0</OUTCOME>
	<OUTCOME>1</OUTCOME>
</VARIABLE>

<VARIABLE TYPE="nature">
	<NAME>v43</NAME>
	<OUTCOME>1</OUTCOME>
	<OUTCOME>0</OUTCOME>
</VARIABLE>

<VARIABLE TYPE="nature">
	<NAME>v44</NAME>
	<OUTCOME>1</OUTCOME>
	<OUTCOME>0</OUTCOME>
</VARIABLE>

<VARIABLE TYPE="nature">
	<NAME>v45</NAME>
	<OUTCOME>999</OUTCOME>
	<OUTCOME>-1</OUTCOME>
</VARIABLE>

<VARIABLE TYPE="nature">
	<NAME>v46</NAME>
	<OUTCOME>1</OUTCOME>
	<OUTCOME>2</OUTCOME>
	<OUTCOME>0</OUTCOME>
	<OUTCOME>3</OUTCOME>
	<OUTCOME>7</OUTCOME>
</VARIABLE>

<VARIABLE TYPE="nature">
	<NAME>v93</NAME>
	<OUTCOME>7</OUTCOME>
	<OUTCOME>8</OUTCOME>
	<OUTCOME>5</OUTCOME>
	<OUTCOME>15</OUTCOME>
	<OUTCOME>4</OUTCOME>
	<OUTCOME>14</OUTCOME>
	<OUTCOME>9</OUTCOME>
	<OUTCOME>13</OUTCOME>
	<OUTCOME>6</OUTCOME>
	<OUTCOME>11</OUTCOME>
	<OUTCOME>32</OUTCOME>
	<OUTCOME>12</OUTCOME>
	<OUTCOME>31</OUTCOME>
	<OUTCOME>10</OUTCOME>
	<OUTCOME>21</OUTCOME>
	<OUTCOME>20</OUTCOME>
</VARIABLE>

<VARIABLE TYPE="nature">
	<NAME>v51</NAME>
	<OUTCOME>0</OUTCOME>
	<OUTCOME>1</OUTCOME>
	<OUTCOME>2</OUTCOME>
	<OUTCOME>3</OUTCOME>
</VARIABLE>

<VARIABLE TYPE="nature">
	<NAME>v52</NAME>
	<OUTCOME>1</OUTCOME>
	<OUTCOME>0</OUTCOME>
</VARIABLE>

<VARIABLE TYPE="nature">
	<NAME>v53</NAME>
	<OUTCOME>1</OUTCOME>
	<OUTCOME>0</OUTCOME>
</VARIABLE>

<DEFINITION>
	<FOR>v1</FOR>
	<GIVEN>v93</GIVEN>
	<TABLE>0.999958951624489 2.05241877552696e-05 2.05241877552696e-05 0.999731291146043 0.000134354426978369 0.000134354426978369 0.999866906235443 6.65468822785653e-05 6.65468822785653e-05 1.92890071947997e-05 0.99996142198561 1.92890071947997e-05 0.99964406478021 0.000177967609894999 0.000177967609894999 1.22688848810532e-05 1.22688848810532e-05 0.999975462230238 0.999947527220255 2.62363898727535e-05 2.62363898727535e-05 3.61023863677389e-05 3.61023863677389e-05 0.999927795227265 0.999871423979428 6.42880102860816e-05 6.42880102860816e-05 0.000181061017562919 0.000181061017562919 0.999637877964874 0.000649772579597141 0.000649772579597141 0.998700454840806 0.000129349372655543 0.000129349372655543 0.999741301254689 0.00258397932816537 0.00258397932816537 0.994832041343669 0.000716845878136201 0.000716845878136201 0.998566308243728 0.996810207336523 0.00159489633173844 0.00159489633173844 0.97979797979798 0.0101010101010101 0.0101010101010101 </TABLE>
</DEFINITION>

<DEFINITION>
	<FOR>v2</FOR>
	<TABLE>0.20814423375816 0.262231893068076 0.0892446378613615 0.43179981349083 0.0085794218215729 </TABLE>
</DEFINITION>

<DEFINITION>
	<FOR>v3</FOR>
	<GIVEN>v2</GIVEN>
	<TABLE>0.999925328554361 7.46714456391876e-05 0.999940730203888 5.92697961119014e-05 0.00017415534656914 0.999825844653431 0.999964005471168 3.59945288316176e-05 0.00181159420289855 0.998188405797101 </TABLE>
</DEFINITION>

<DEFINITION>
	<FOR>v4</FOR>
	<GIVEN>v27</GIVEN>
	<TABLE>0.999970435193945 2.95648060548723e-05 0.000278551532033426 0.999721448467967 0.000840336134453782 0.999159663865546 </TABLE>
</DEFINITION>

<DEFINITION>
	<FOR>v5</FOR>
	<GIVEN>v1</GIVEN>
	<TABLE>0.999939024390244 6.09756097560976e-05 0.000154273372415921 0.999845726627584 0.999936394860705 6.36051392952551e-05 </TABLE>
</DEFINITION>

<DEFINITION>
	<FOR>v6</FOR>
	<GIVEN>v1</GIVEN>
	<TABLE>0.999939024390244 6.09756097560976e-05 0.000154273372415921 0.999845726627584 0.319488614680066 0.680511385319934 </TABLE>
</DEFINITION>

<DEFINITION>
	<FOR>v7</FOR>
	<GIVEN>v26</GIVEN>
	<GIVEN>v1</GIVEN>
	<TABLE>0.408676368676369 0.591295911295911 2.77200277200277e-05 5.14323921205575e-05 5.14323921205575e-05 0.999897135215759 0.776835965092168 0.223141249117051 2.2785790780869e-05 0.255161904761905 0.744761904761905 7.61904761904762e-05 0.333333333333333 0.333333333333333 0.333333333333333 0.626105519975602 0.373589508996645 0.000304971027752364 </TABLE>
</DEFINITION>

<DEFINITION>
	<FOR>v8</FOR>
	<GIVEN>v5</GIVEN>
	<TABLE>0.999953301578407 4.66984215933501e-05 0.0002313743637205 0.99976862563628 </TABLE>
</DEFINITION>

<DEFINITION>
	<FOR>v9</FOR>
	<GIVEN>v5</GIVEN>
	<TABLE>0.999953301578407 4.66984215933501e-05 0.0002313743637205 0.99976862563628 </TABLE>
</DEFINITION>

<DEFINITION>
	<FOR>v10</FOR>
	<GIVEN>v1</GIVEN>
	<TABLE>0.999939024390244 6.09756097560976e-05 0.000154273372415921 0.999845726627584 6.36051392952551e-05 0.999936394860705 </TABLE>
</DEFINITION>

<DEFINITION>
	<FOR>v11</FOR>
	<GIVEN>v1</GIVEN>
	<TABLE>0.999939024390244 6.09756097560976e-05 0.000154273372415921 0.999845726627584 0.0393715812237629 0.960628418776237 </TABLE>
</DEFINITION>

<DEFINITION>
	<FOR>v12</FOR>
	<GIVEN>v24</GIVEN>
	<TABLE>0.99996303415644 3.69658435605501e-05 0.999907252828789 9.27471712112781e-05 0.999961834974429 3.81650255705671e-05 0.00354609929078014 0.99645390070922 0.954545454545454 0.0454545454545455 </TABLE>
</DEFINITION>

<DEFINITION>
	<FOR>v13</FOR>
	<GIVEN>v4</GIVEN>
	<TABLE>0.999955654101996 4.43458980044346e-05 0.000313873195229127 0.999686126804771 </TABLE>
</DEFINITION>

<DEFINITION>
	<FOR>v14</FOR>
	<GIVEN>v5</GIVEN>
	<TABLE>0.999953301578407 4.66984215933501e-05 0.0002313743637205 0.99976862563628 </TABLE>
</DEFINITION>

<DEFINITION>
	<FOR>v15</FOR>
	<GIVEN>v10</GIVEN>
	<TABLE>0.999908542162063 9.14578379367112e-05 6.75584380489123e-05 0.999932441561951 </TABLE>
</DEFINITION>

<DEFINITION>
	<FOR>v16</FOR>
	<GIVEN>v93</GIVEN>
	<TABLE>0.999969213718367 3.07862816329044e-05 0.000201531640467553 0.999798468359532 0.999900179676582 9.98203234178479e-05 2.89335107921995e-05 0.999971066489208 0.000266951414842499 0.999733048585158 0.999981596672678 1.84033273215797e-05 0.999960645415191 3.93545848091303e-05 0.999945846420448 5.41535795516084e-05 9.64320154291225e-05 0.999903567984571 0.999728408473656 0.000271591526344378 0.999025341130604 0.000974658869395711 0.000194024058983314 0.999805975941017 0.00387596899224806 0.996124031007752 0.0010752688172043 0.998924731182796 0.997607655502392 0.00239234449760766 0.0151515151515152 0.984848484848485 </TABLE>
</DEFINITION>

<DEFINITION>
	<FOR>v17</FOR>
	<GIVEN>v1</GIVEN>
	<TABLE>0.999542682926829 3.04878048780488e-05 3.04878048780488e-05 0.000396341463414634 7.71366862079605e-05 0.999768589941376 7.71366862079605e-05 7.71366862079605e-05 3.18025696476275e-05 3.18025696476275e-05 0.999904592291057 3.18025696476275e-05 </TABLE>
</DEFINITION>

<DEFINITION>
	<FOR>v18</FOR>
	<GIVEN>v5</GIVEN>
	<TABLE>0.999953301578407 4.66984215933501e-05 0.0002313743637205 0.99976862563628 </TABLE>
</DEFINITION>

<DEFINITION>
	<FOR>v19</FOR>
	<GIVEN>v52</GIVEN>
	<GIVEN>v1</GIVEN>
	<TABLE>0.323311160113825 0.114199705373727 0.0178514241794841 0.052108590826326 0.143461035217904 0.0621002644316549 0.0356936984747143 0.0642413373470826 0.133469361612576 0.0356936984747143 0.0171377332076749 9.14988425396419e-06 0.000722840856063171 0.635593373113879 0.277027636062087 1.80274377602711e-05 0.00283030772836257 0.00423644787366372 0.0464206522326982 0.00283030772836257 0.00142416758306142 0.0253285500531809 0.00423644787366372 1.80274377602711e-05 1.80274377602711e-05 1.80274377602711e-05 0.552516848710202 0.165326516383918 0.00508482454101789 0.0130606553567279 0.0493144317917732 0.0942691145712294 0.0108854287706251 0.0224866372298396 0.0681663955379967 0.0108854287706251 0.00798512665582152 9.29584011155008e-06 9.29584011155008e-06 0.270996737529954 0.164403468419482 0.0127707898257129 0.0510542878865161 0.159899527471153 0.0540569151854026 0.0285345831448671 0.0585608561337324 0.125369313533958 0.0488023174123512 0.024781299021259 0.000760280630166781 9.62380544514912e-06 0.352179197777392 0.176106963014412 3.47282514325404e-05 0.00816113908664699 0.0677548185448863 0.357596805000868 0.00816113908664699 0.00816113908664699 0.00816113908664699 0.00816113908664699 0.00274353186317069 0.00274353186317069 3.47282514325404e-05 0.410108355455475 0.273946142483809 0.00323310367623514 0.0169298943301898 0.0692999762423692 0.0918593961430003 0.011290039355032 0.0225697493053475 0.0692999762423692 0.0153185071944304 0.0161242007623101 1.03294047164062e-05 1.03294047164062e-05 </TABLE>
</DEFINITION>

<DEFINITION>
	<FOR>v21</FOR>
	<GIVEN>v33</GIVEN>
	<GIVEN>v26</GIVEN>
	<GIVEN>v10</GIVEN>
	<TABLE>0.913358703497146 0.0866412965028541 0.999982234855214 1.776514478593e-05 0.797729516288253 0.202270483711747 0.999656829100892 0.000343170899107756 0.706809583858764 0.293190416141236 0.5 0.5 0.718465539661899 0.281534460338101 0.5 0.5 </TABLE>
</DEFINITION>

<DEFINITION>
	<FOR>v23</FOR>
	<TABLE>7.77121541809139e-05 0.999922287845819 </TABLE>
</DEFINITION>

<DEFINITION>
	<FOR>v24</FOR>
	<GIVEN>v1</GIVEN>
	<TABLE>0.989658536585366 2.4390243902439e-05 2.4390243902439e-05 0.0102682926829268 2.4390243902439e-05 6.17093489663684e-05 0.997901882135144 6.17093489663684e-05 6.17093489663684e-05 0.00191298981795742 2.5442055718102e-05 2.5442055718102e-05 0.999898231777128 2.5442055718102e-05 2.5442055718102e-05 </TABLE>
</DEFINITION>

<DEFINITION>
	<FOR>v25</FOR>
	<GIVEN>v1</GIVEN>
	<TABLE>0.860914634146342 0.139085365853659 0.999845726627584 0.000154273372415921 0.95146927871772 0.0485307212822796 </TABLE>
</DEFINITION>

<DEFINITION>
	<FOR>v26</FOR>
	<GIVEN>v25</GIVEN>
	<GIVEN>v1</GIVEN>
	<TABLE>0.771336496919045 0.228663503080955 0.999922851411819 7.71485881808363e-05 0.940203222140517 0.0597967778594826 0.497369574747918 0.502630425252082 0.5 0.5 0.739842726081258 0.260157273918742 </TABLE>
</DEFINITION>

<DEFINITION>
	<FOR>v27</FOR>
	<GIVEN>v93</GIVEN>
	<TABLE>0.999958951624489 2.05241877552696e-05 2.05241877552696e-05 0.000134354426978369 0.999731291146043 0.000134354426978369 0.999866906235443 6.65468822785653e-05 6.65468822785653e-05 0.99996142198561 1.92890071947997e-05 1.92890071947997e-05 0.000177967609894999 0.99964406478021 0.000177967609894999 0.999975462230238 1.22688848810532e-05 1.22688848810532e-05 0.999947527220255 2.62363898727535e-05 2.62363898727535e-05 0.999927795227265 3.61023863677389e-05 3.61023863677389e-05 6.42880102860816e-05 0.999871423979428 6.42880102860816e-05 0.999637877964874 0.000181061017562919 0.000181061017562919 0.998700454840806 0.000649772579597141 0.000649772579597141 0.000129349372655543 0.000129349372655543 0.999741301254689 0.00258397932816537 0.00258397932816537 0.994832041343669 0.000716845878136201 0.000716845878136201 0.998566308243728 0.996810207336523 0.00159489633173844 0.00159489633173844 0.0101010101010101 0.97979797979798 0.0101010101010101 </TABLE>
</DEFINITION>

<DEFINITION>
	<FOR>v28</FOR>
	<GIVEN>v1</GIVEN>
	<TABLE>0.999918699186992 4.0650406504065e-05 4.0650406504065e-05 0.000102848914943947 0.999794302170112 0.000102848914943947 0.182080312089217 4.24034261968367e-05 0.817877284484586 </TABLE>
</DEFINITION>

<DEFINITION>
	<FOR>v29</FOR>
	<TABLE>7.77121541809139e-05 0.999922287845819 </TABLE>
</DEFINITION>

<DEFINITION>
	<FOR>v30</FOR>
	<TABLE>7.77121541809139e-05 0.999922287845819 </TABLE>
</DEFINITION>

<DEFINITION>
	<FOR>v31</FOR>
	<GIVEN>v10</GIVEN>
	<TABLE>0.999908542162063 9.14578379367112e-05 6.75584380489123e-05 0.999932441561951 </TABLE>
</DEFINITION>

<DEFINITION>
	<FOR>v32</FOR>
	<GIVEN>v28</GIVEN>
	<TABLE>0.999948084311079 5.1915688921192e-05 0.000154273372415921 0.999845726627584 7.77604976671851e-05 0.999922239502333 </TABLE>
</DEFINITION>

<DEFINITION>
	<FOR>v33</FOR>
	<GIVEN>v26</GIVEN>
	<GIVEN>v24</GIVEN>
	<TABLE>0.951736093663635 0.048263906336365 0.999953622112977 4.63778870234672e-05 0.999979492227554 2.05077724457569e-05 0.783687943262411 0.216312056737589 0.976190476190476 0.0238095238095238 0.879667179415466 0.120332820584534 0.5 0.5 0.999725425590335 0.000274574409665019 0.287234042553191 0.712765957446808 0.5 0.5 </TABLE>
</DEFINITION>

<DEFINITION>
	<FOR>v34</FOR>
	<TABLE>7.77121541809139e-05 0.999922287845819 </TABLE>
</DEFINITION>

<DEFINITION>
	<FOR>v35</FOR>
	<GIVEN>v10</GIVEN>
	<TABLE>0.999908542162063 9.14578379367112e-05 6.75584380489123e-05 0.999932441561951 </TABLE>
</DEFINITION>

<DEFINITION>
	<FOR>v36</FOR>
	<GIVEN>v93</GIVEN>
	<TABLE>0.999958951624489 2.05241877552696e-05 2.05241877552696e-05 0.000134354426978369 0.999731291146043 0.000134354426978369 6.65468822785653e-05 0.999866906235443 6.65468822785653e-05 0.99996142198561 1.92890071947997e-05 1.92890071947997e-05 0.000177967609894999 0.99964406478021 0.000177967609894999 0.999975462230238 1.22688848810532e-05 1.22688848810532e-05 0.998688180506362 2.62363898727535e-05 0.00128558310376492 0.999927795227265 3.61023863677389e-05 3.61023863677389e-05 6.42880102860816e-05 0.999871423979428 6.42880102860816e-05 0.000181061017562919 0.999637877964874 0.000181061017562919 0.000649772579597141 0.998700454840806 0.000649772579597141 0.000129349372655543 0.999741301254689 0.000129349372655543 0.00258397932816537 0.994832041343669 0.00258397932816537 0.000716845878136201 0.998566308243728 0.000716845878136201 0.00159489633173844 0.996810207336523 0.00159489633173844 0.0101010101010101 0.97979797979798 0.0101010101010101 </TABLE>
</DEFINITION>

<DEFINITION>
	<FOR>v37</FOR>
	<GIVEN>v10</GIVEN>
	<TABLE>0.999908542162063 9.14578379367112e-05 6.75584380489123e-05 0.999932441561951 </TABLE>
</DEFINITION>

<DEFINITION>
	<FOR>v38</FOR>
	<GIVEN>v32</GIVEN>
	<GIVEN>v7</GIVEN>
	<TABLE>0.939153100029911 0.0584967739178738 0.00235012605221553 2.90841404182299e-05 0.614635139458453 0.385335776401128 0.333333333333333 0.333333333333333 0.333333333333333 0.954405422057917 0.0443947206278172 0.00119985731426533 0.000129148908691722 0.816091954022989 0.18377889706832 0.999897135215759 5.14323921205575e-05 5.14323921205575e-05 </TABLE>
</DEFINITION>

<DEFINITION>
	<FOR>v39</FOR>
	<GIVEN>v10</GIVEN>
	<TABLE>0.999908542162063 9.14578379367112e-05 6.75584380489123e-05 0.999932441561951 </TABLE>
</DEFINITION>

<DEFINITION>
	<FOR>v40</FOR>
	<TABLE>7.77121541809139e-05 0.999922287845819 </TABLE>
</DEFINITION>

<DEFINITION>
	<FOR>v41</FOR>
	<GIVEN>v5</GIVEN>
	<TABLE>0.999953301578407 4.66984215933501e-05 0.0002313743637205 0.99976862563628 </TABLE>
</DEFINITION>

<DEFINITION>
	<FOR>v42</FOR>
	<GIVEN>v3</GIVEN>
	<TABLE>0.999956929968128 4.30700318718236e-05 0.00039714058776807 0.999602859412232 </TABLE>
</DEFINITION>

<DEFINITION>
	<FOR>v43</FOR>
	<GIVEN>v16</GIVEN>
	<TABLE>0.999945145364783 5.48546352166758e-05 0.000133226751931788 0.999866773248068 </TABLE>
</DEFINITION>

<DEFINITION>
	<FOR>v44</FOR>
	<GIVEN>v7</GIVEN>
	<TABLE>0.951161504424779 0.0488384955752212 0.899088448938898 0.100911551061102 0.000154273372415921 0.999845726627584 </TABLE>
</DEFINITION>

<DEFINITION>
	<FOR>v45</FOR>
	<TABLE>7.77121541809139e-05 0.999922287845819 </TABLE>
</DEFINITION>

<DEFINITION>
	<FOR>v46</FOR>
	<GIVEN>v2</GIVEN>
	<TABLE>0.999880525686977 2.9868578255675e-05 2.9868578255675e-05 2.9868578255675e-05 2.9868578255675e-05 2.37079184447606e-05 0.999905168326221 2.37079184447606e-05 2.37079184447606e-05 2.37079184447606e-05 6.96621386276559e-05 6.96621386276559e-05 0.999721351445489 6.96621386276559e-05 6.96621386276559e-05 1.4397811532647e-05 1.4397811532647e-05 1.4397811532647e-05 0.999942408753869 1.4397811532647e-05 0.00072463768115942 0.00072463768115942 0.00072463768115942 0.00072463768115942 0.997101449275362 </TABLE>
</DEFINITION>

<DEFINITION>
	<FOR>v93</FOR>
	<GIVEN>v2</GIVEN>
	<TABLE>0.757924507168459 9.33393070489845e-06 9.33393070489845e-06 9.33393070489845e-06 9.33393070489845e-06 9.33393070489845e-06 9.33393070489845e-06 9.33393070489845e-06 0.241944817801673 9.33393070489845e-06 9.33393070489845e-06 9.33393070489845e-06 9.33393070489845e-06 9.33393070489845e-06 9.33393070489845e-06 9.33393070489845e-06 7.40872451398767e-06 0.0918755926979611 7.40872451398767e-06 7.40872451398767e-06 7.40872451398767e-06 7.40872451398767e-06 0.470609589853011 0.341994132290185 7.40872451398767e-06 7.40872451398767e-06 7.40872451398767e-06 0.0954317804646752 7.40872451398767e-06 7.40872451398767e-06 7.40872451398767e-06 7.40872451398767e-06 2.17694183211425e-05 2.17694183211425e-05 0.545128004179728 2.17694183211425e-05 0.203783524904215 2.17694183211425e-05 2.17694183211425e-05 2.17694183211425e-05 2.17694183211425e-05 0.200300417972832 2.17694183211425e-05 2.17694183211425e-05 2.17694183211425e-05 0.0505268199233716 2.17694183211425e-05 2.17694183211425e-05 4.4993161039522e-06 4.4993161039522e-06 4.4993161039522e-06 0.388745410697574 4.4993161039522e-06 0.611191598876971 4.4993161039522e-06 4.4993161039522e-06 4.4993161039522e-06 4.4993161039522e-06 4.4993161039522e-06 4.4993161039522e-06 4.4993161039522e-06 4.4993161039522e-06 4.4993161039522e-06 4.4993161039522e-06 0.000226449275362319 0.000226449275362319 0.000226449275362319 0.000226449275362319 0.000226449275362319 0.000226449275362319 0.000226449275362319 0.000226449275362319 0.000226449275362319 0.000226449275362319 0.579936594202899 0.000226449275362319 0.145153985507246 0.000226449275362319 0.235733695652174 0.0364583333333333 </TABLE>
</DEFINITION>

<DEFINITION>
	<FOR>v51</FOR>
	<GIVEN>v7</GIVEN>
	<TABLE>0.120160398230088 0.360425884955752 0.314297566371681 0.205116150442478 0.163687508901866 0.319220908702464 0.298283720267768 0.218807862127902 0.0528386300524529 0.32867941993212 0.209271829682197 0.409210120333231 </TABLE>
</DEFINITION>

<DEFINITION>
	<FOR>v52</FOR>
	<GIVEN>v51</GIVEN>
	<TABLE>0.725615456528514 0.274384543471486 0.611047640808866 0.388952359191134 6.68002672010688e-05 0.999933199732799 0.999920496104309 7.95038956908888e-05 </TABLE>
</DEFINITION>

<DEFINITION>
	<FOR>v53</FOR>
	<GIVEN>v52</GIVEN>
	<TABLE>0.999928397536875 7.16024631247315e-05 8.49617672047579e-05 0.999915038232795 </TABLE>
</DEFINITION>

</NETWORK>
</BIF>
